<?xml version="1.0" encoding="UTF-8"?>
<!DOCTYPE generatorConfiguration PUBLIC "-//mybatis.org//DTD MyBatis Generator Configuration 1.0//EN" "http://mybatis.org/dtd/mybatis-generator-config_1_0.dtd">
<generatorConfiguration>
	<classPathEntry
		location="C:\Users\tinygone\.gradle\caches\modules-2\files-2.1\org.xerial\sqlite-jdbc\3.15.1\acb44214a86abebf2f3a8969ecbb697850dd9c8e\sqlite-jdbc-3.15.1.jar" />
	<context id="context1">
		<jdbcConnection connectionURL="jdbc:sqlite::resource:file:///C:/sqlite/test.s3db"
			driverClass="org.sqlite.JDBC" password="" userId="" />
		<javaTypeResolver>
			<property name="forceBigDecimals" value="false" />
		</javaTypeResolver>
		<javaModelGenerator targetPackage="com.ty.prop.scan.domain"
			targetProject="MyLib">
			<property name="enableSubPackages" value="true" />
			<property name="trimStrings" value="true" />
		</javaModelGenerator>
		<sqlMapGenerator targetPackage="com.ty.prop.scan.mapping"
			targetProject="MyLib">
			<property name="enableSubPackages" value="true" />
		</sqlMapGenerator>
		<javaClientGenerator targetPackage="com.ty.prop.scan.dao"
			targetProject="MyLib" type="XMLMAPPER">
			<property name="enableSubPackages" value="true" />
		</javaClientGenerator>
		<!-- <table tableName="system_menu" enableCountByExample="false"
			enableUpdateByExample="false" enableDeleteByExample="false"
			enableSelectByExample="false" selectByExampleQueryId="false">
			<columnOverride column="id_system_menu" property="menuId" />
			<columnOverride column="menu_name" property="menuName" />
			<columnOverride column="menu_url" property="menuUrl" />
			<columnOverride column="id_parent_menu" property="parentMenuId" />
			<columnOverride column="sort_num" property="sortNum" />
			<columnOverride column="menu_icon" property="menuIcon" />
			<columnOverride column="menu_level" property="menuLevel" />
			<columnOverride column="auth_flag" property="authFlag" />
		</table> -->
		<table tableName="a" enableCountByExample="false"
			enableUpdateByExample="false" enableDeleteByExample="false"
			enableSelectByExample="false" selectByExampleQueryId="false">
			<columnOverride column="a_id" property="aId" />
		</table>

		

	</context>
</generatorConfiguration>